{
  "schema_version": "dashboard.snapshot.v1",
  "step": 1,
  "mode": "replay",
  "generated_at": "2026-07-10T04:10:00+09:00",
  "summary": {
    "active_story_count": 1,
    "max_mission_impact": "SUSTAINED",
    "hitl_pending_count": 0,
    "decision_advantage": "margin",
    "cpcon_level": 4
  },
  "stories": [
    {
      "story_id": "OP-077",
      "actor": "OP-077",
      "campaign_id": "C1",
      "campaign_name": "GCS 침해 → CT 하향 → 야간 C4I → 무장 명령 (캠페인 C1)",
      "matched": 1,
      "total": 4,
      "next_expected": "S37-CT-LEVEL-TAMPER",
      "target_asset": "GCS",
      "mission_impact": "SUSTAINED",
      "hitl_status": "NOT_REQUIRED",
      "decision_options": [],
      "alerts": [
        {
          "alert_id": "ALERT-GCS-0341",
          "scenario_id": "S34-OPERATOR-BRUTEFORCE",
          "title": "GCS 운용자 계정 브루트포스 후 비인가 로그인 성공",
          "tactic": "InitialAccess",
          "technique": "T1078",
          "order": 1
        }
      ]
    }
  ],
  "selected_story_id": "OP-077",
  "navigator": [
    {
      "tactic": "Reconnaissance",
      "order": 1,
      "observed": false,
      "current": false,
      "predicted": false,
      "gap": false,
      "observed_order": null,
      "note": ""
    },
    {
      "tactic": "ResourceDevelopment",
      "order": 2,
      "observed": false,
      "current": false,
      "predicted": false,
      "gap": true,
      "observed_order": null,
      "note": ""
    },
    {
      "tactic": "InitialAccess",
      "order": 3,
      "observed": true,
      "current": true,
      "predicted": false,
      "gap": false,
      "observed_order": 1,
      "note": ""
    },
    {
      "tactic": "Execution",
      "order": 4,
      "observed": false,
      "current": false,
      "predicted": false,
      "gap": false,
      "observed_order": null,
      "note": ""
    },
    {
      "tactic": "Persistence",
      "order": 5,
      "observed": false,
      "current": false,
      "predicted": false,
      "gap": false,
      "observed_order": null,
      "note": ""
    },
    {
      "tactic": "PrivilegeEscalation",
      "order": 6,
      "observed": false,
      "current": false,
      "predicted": false,
      "gap": false,
      "observed_order": null,
      "note": ""
    },
    {
      "tactic": "StealthEvasion",
      "order": 7,
      "observed": false,
      "current": false,
      "predicted": true,
      "gap": false,
      "observed_order": null,
      "note": ""
    },
    {
      "tactic": "Discovery",
      "order": 8,
      "observed": false,
      "current": false,
      "predicted": false,
      "gap": false,
      "observed_order": null,
      "note": ""
    },
    {
      "tactic": "LateralMovement",
      "order": 9,
      "observed": false,
      "current": false,
      "predicted": false,
      "gap": false,
      "observed_order": null,
      "note": ""
    },
    {
      "tactic": "Collection",
      "order": 10,
      "observed": false,
      "current": false,
      "predicted": false,
      "gap": true,
      "observed_order": null,
      "note": ""
    },
    {
      "tactic": "CommandAndControl",
      "order": 11,
      "observed": false,
      "current": false,
      "predicted": false,
      "gap": true,
      "observed_order": null,
      "note": ""
    },
    {
      "tactic": "Exfiltration",
      "order": 12,
      "observed": false,
      "current": false,
      "predicted": false,
      "gap": false,
      "observed_order": null,
      "note": ""
    },
    {
      "tactic": "ImpairProcessControl",
      "order": 13,
      "observed": false,
      "current": false,
      "predicted": false,
      "gap": false,
      "observed_order": null,
      "note": ""
    },
    {
      "tactic": "InhibitResponseFunction",
      "order": 14,
      "observed": false,
      "current": false,
      "predicted": false,
      "gap": true,
      "observed_order": null,
      "note": ""
    },
    {
      "tactic": "Impact",
      "order": 15,
      "observed": false,
      "current": false,
      "predicted": false,
      "gap": false,
      "observed_order": null,
      "note": ""
    }
  ],
  "topology": {
    "nodes": [
      {
        "id": "gcs-qgc",
        "label": "GCS/MCE QGroundControl",
        "plane": "ground",
        "kind": "ground_control_station",
        "status": "SUSTAINED",
        "active": true,
        "metadata": {}
      },
      {
        "id": "auth-stub",
        "label": "Operator Authentication",
        "plane": "ground",
        "kind": "identity",
        "status": "STUB",
        "active": true,
        "metadata": {}
      }
    ],
    "edges": []
  },
  "bluf": {
    "situation": "OP-077 계정이 브루트포스 후 GCS에 비인가 로그인했습니다.",
    "mission_impact": "현재 임무 지속 가능. GCS 접근 신뢰도 저하 감시 필요.",
    "recommendation": "해당 운용자 세션 격리 및 자격증명 재발급.",
    "next_move": "다음 예상 수순은 S37 CT 레벨 하향입니다.",
    "confidence": "medium",
    "hitl_badge": "NOT_REQUIRED",
    "caveats": [
      "replay demo dataset"
    ]
  },
  "source": {
    "alert_id": "ALERT-GCS-0341",
    "scenario_id": "S34-OPERATOR-BRUTEFORCE",
    "trace": [
      "UAVOpAudit_CL"
    ]
  }
}
